qng/__init__.py
qng/cli.py
qng/generator.py
qng/data/names.json
qng/data/surnames.json
qng-1.0.1.dist-info/METADATA
qng-1.0.1.dist-info/RECORD
qng-1.0.1.dist-info/WHEEL
qng-1.0.1.dist-info/entry_points.txt
qng-1.0.1.dist-info/top_level.txt
