Metadata-Version: 2.1
Name: qng
Version: 1.0.1
Summary: The Queb name generator
Home-page: https://github.com/abusque/qng
Author: Antoine Busque
Author-email: antoinebusque@gmail.com
License: MIT
Keywords: name,generator,quebec
Platform: UNKNOWN
Classifier: License :: OSI Approved :: MIT License
Classifier: Programming Language :: Python
Classifier: Programming Language :: Python :: 3
Classifier: Programming Language :: Python :: 3.4
Classifier: Programming Language :: Python :: 3.5
Classifier: Programming Language :: Python :: 3.6
